mderanklib/__init__.py
mderanklib/mderank_main.py
mderanklib-0.1.0.dist-info/LICENSE
mderanklib-0.1.0.dist-info/METADATA
mderanklib-0.1.0.dist-info/WHEEL
mderanklib-0.1.0.dist-info/top_level.txt
mderanklib-0.1.0.dist-info/RECORD
