Metadata-Version: 2.1
Name: mderanklib
Version: 0.1.0
Summary: Librería para realizar ranking multilingüe de entidades.
Home-page: https://github.com/oeg-upm/mderanklib
Author: Pablo Calleja
Author-email: pablo@gmail.com
License: Apache
License-File: LICENSE
Requires-Dist: pandas==1.3.5
Requires-Dist: StanfordCoreNLP==3.9.1.1
Requires-Dist: transformers==4.37.2
Requires-Dist: accelerate==0.5.1
Requires-Dist: pke==2.0.0
Requires-Dist: torch==2.1.2
Requires-Dist: torchvision==0.16.2
Requires-Dist: torchaudio==2.1.2
Requires-Dist: nltk==3.8.1
Requires-Dist: allennlp==3.1.0
